update_reqs/__init__.py
update_reqs/cli.py
update_reqs/commands.py
update_reqs/helpers.py
update_reqs/parsers.py
update_reqs-1.2.0.dist-info/licenses/LICENSE
update_reqs-1.2.0.dist-info/METADATA
update_reqs-1.2.0.dist-info/WHEEL
update_reqs-1.2.0.dist-info/entry_points.txt
update_reqs-1.2.0.dist-info/top_level.txt
update_reqs-1.2.0.dist-info/RECORD
